CHANGES.rst
LICENSE.rst
MANIFEST.in
README.rst
VERSION.txt
setup.cfg
setup.py
examples/publisher.py
examples/server.py
examples/subscriber.py
src/inbus/__init__.py
src/inbus/client/__init__.py
src/inbus/client/publisher.py
src/inbus/client/subscriber.py
src/inbus_client.egg-info/PKG-INFO
src/inbus_client.egg-info/SOURCES.txt
src/inbus_client.egg-info/dependency_links.txt
src/inbus_client.egg-info/not-zip-safe
src/inbus_client.egg-info/requires.txt
src/inbus_client.egg-info/top_level.txt