Metadata-Version: 1.1
Name: inbus-client
Version: 1.1.0
Summary: Python client for inbus
Home-page: https://github.com/mlos/inbus.client.python
Author: Maarten Los
Author-email: mlos@gmx.com
License: BSD 2-Clause license
Download-URL: https://github.com/mlos/inbus.client.python/tarball/1.1.0
Keywords: client inbus publisher subscriber pub sub
Platform: UNKNOWN
Classifier: License :: OSI Approved :: BSD License
Classifier: Development Status :: 5 - Production/Stable
Classifier: Intended Audience :: Information Technology
Classifier: Intended Audience :: Developers
Classifier: Topic :: Education
Classifier: Topic :: System :: Networking
Classifier: Topic :: System :: Distributed Computing
Classifier: Programming Language :: Python :: 2
Classifier: Programming Language :: Python :: 2.7
Classifier: Programming Language :: Python :: 3
Classifier: Programming Language :: Python :: 3.4
Classifier: Programming Language :: Python :: 3.5
Classifier: Programming Language :: Python :: 3.6
